syslog2irc/__init__.py
syslog2irc/cli.py
syslog2irc/config.py
syslog2irc/formatting.py
syslog2irc/irc.py
syslog2irc/main.py
syslog2irc/network.py
syslog2irc/routing.py
syslog2irc/signals.py
syslog2irc/syslog.py
syslog2irc/util.py
syslog2irc-0.13.dist-info/LICENSE
syslog2irc-0.13.dist-info/METADATA
syslog2irc-0.13.dist-info/WHEEL
syslog2irc-0.13.dist-info/entry_points.txt
syslog2irc-0.13.dist-info/top_level.txt
syslog2irc-0.13.dist-info/RECORD
