Metadata-Version: 2.1
Name: syslog2irc
Version: 0.13
Summary: Forward syslog messages to IRC
Home-page: https://homework.nwsnet.de/releases/c474/#syslog2irc
Author: Jochen Kupperschmidt
Author-email: homework@nwsnet.de
License: MIT
Keywords: irc,syslog
Platform: any
Classifier: Environment :: Console
Classifier: Intended Audience :: System Administrators
Classifier: License :: OSI Approved :: MIT License
Classifier: Operating System :: OS Independent
Classifier: Programming Language :: Python
Classifier: Programming Language :: Python :: 3
Classifier: Programming Language :: Python :: 3.7
Classifier: Programming Language :: Python :: 3.8
Classifier: Programming Language :: Python :: 3.9
Classifier: Topic :: Communications :: Chat :: Internet Relay Chat
Classifier: Topic :: Internet
Classifier: Topic :: System :: Logging
Classifier: Topic :: System :: Monitoring
Classifier: Topic :: System :: Networking :: Monitoring
Classifier: Topic :: System :: Systems Administration
Requires-Python: >=3.7
Requires-Dist: blinker (==1.4)
Requires-Dist: irc (==19.0.1)
Requires-Dist: rtoml (==0.6.1)
Requires-Dist: syslogmp (==0.4)
